<?xml version="1.0" encoding="UTF-8"?>
<beans xmlns="http://www.springframework.org/schema/beans"
       xmlns:context="http://www.springframework.org/schema/context"
       xmlns:task="http://www.springframework.org/schema/task"
       xmlns:mvc="http://www.springframework.org/schema/mvc" xmlns:xsi="http://www.w3.org/2001/XMLSchema-instance"
       xsi:schemaLocation="
        http://www.springframework.org/schema/beans
        http://www.springframework.org/schema/beans/spring-beans-4.0.xsd
        http://www.springframework.org/schema/context
        http://www.springframework.org/schema/context/spring-context-4.0.xsd
        http://www.springframework.org/schema/mvc
        http://www.springframework.org/schema/mvc/spring-mvc-4.0.xsd
        http://www.springframework.org/schema/task
        http://www.springframework.org/schema/task/spring-task-3.0.xsd
        ">

    <bean class="org.springframework.web.servlet.mvc.method.annotation.RequestMappingHandlerAdapter">
        <property name="messageConverters">
            <list>
                <bean class="org.springframework.http.converter.json.GsonHttpMessageConverter"/>
                <bean class="org.springframework.http.converter.ByteArrayHttpMessageConverter"/>
                <bean class="org.springframework.http.converter.StringHttpMessageConverter"/>
            </list>
        </property>
    </bean>

    <context:component-scan base-package="com.inter3i.sun.api.ota.v1"/>

    <!-- 使Spring关注Annotation -->
    <context:annotation-config/>
    <!-- 使用annotation 自动注册bean,并检查@Required,@Autowired的属性已被注入 -->
    <mvc:annotation-driven/>


    <!-- 开启这个配置，spring才能识别@Scheduled注解-->
<!--    <task:annotation-driven scheduler="sgScheduler" executor="sgExecutor" mode="proxy"/>
    <task:scheduled-tasks scheduler="sgScheduler">
        &lt;!&ndash; ***************************************** 数据入库定时任务 ***************************************** &ndash;&gt;
        &lt;!&ndash; 8081端口 &ndash;&gt;
        <task:scheduled ref="importJob" method="importDoc2SolrFromCache1" cron="0 0 1,4,7,22 * * ?"/>
        &lt;!&ndash;<task:scheduled ref="importJob" method="importDoc2SolrFromCache1" cron="1 * * * * ?"/>&ndash;&gt;

        &lt;!&ndash; 8071端口  &ndash;&gt;
        <task:scheduled ref="importJob" method="importDoc2SolrFromCache2" cron="0 0 2,5,8,23 * * ?"/>
        &lt;!&ndash;<task:scheduled ref="importJob" method="importDoc2SolrFromCache2" cron="1 * * * * ?"/>&ndash;&gt;


        &lt;!&ndash;7011端口 &ndash;&gt;
        <task:scheduled ref="importJob" method="importDoc2SolrFromCache3" cron="0 0 0,3,6,21 * * ?"/>
        &lt;!&ndash;<task:scheduled ref="importJob" method="importDoc2SolrFromCache3" cron="1 * * * * ?"/>&ndash;&gt;


        &lt;!&ndash; 7021端口 &ndash;&gt;
        <task:scheduled ref="importJob" method="importDoc2SolrFromCache4" cron="0 30 1,4,7,22 * * ?"/>
        &lt;!&ndash;<task:scheduled ref="importJob" method="importDoc2SolrFromCache4" cron="1 * * * * ?"/>&ndash;&gt;

        &lt;!&ndash; ***************************************** 数据入库定时任务 *****************************************&ndash;&gt;

        &lt;!&ndash;***************************************** 分词定时任务 *****************************************&ndash;&gt;
        &lt;!&ndash;8081端口&ndash;&gt;
        &lt;!&ndash;<task:scheduled ref="segmenteJob" method="segmentDocs4Cache1" cron="1 * * * * ?"/>&ndash;&gt;
        <task:scheduled ref="segmenteJob" method="segmentDocs4Cache1" cron="0 0,20,40 * * * ?"/>

        &lt;!&ndash; 8071端口 &ndash;&gt;
        <task:scheduled ref="segmenteJob" method="segmentDocs4Cache2" cron="15 5,25,45 * * * ?"/>
        &lt;!&ndash;<task:scheduled ref="segmenteJob" method="segmentDocs4Cache2" cron="1 * * * * ?"/>&ndash;&gt;


        &lt;!&ndash; 7011端口 &ndash;&gt;
        <task:scheduled ref="segmenteJob" method="segmentDocs4Cache3" cron="30 10,30,50 * * * ?"/>

        &lt;!&ndash; 7021端口 &ndash;&gt;
        <task:scheduled ref="segmenteJob" method="segmentDocs4Cache4" cron="45 15,35,55 * * * ?"/>
        &lt;!&ndash; ***************************************** 分词定时任务 ***************************************** &ndash;&gt;


        &lt;!&ndash; ***************************************** 测试类 ***************************************** &ndash;&gt;
        &lt;!&ndash;<task:scheduled ref="importJobTest" method="segmentDocs4CacheTest" cron="1 * * * * ?"/>&ndash;&gt;
        &lt;!&ndash; ***************************************** 测试类 ***************************************** &ndash;&gt;
    </task:scheduled-tasks>
    <task:scheduler id="sgScheduler" pool-size="10"/>
    <task:executor id="sgExecutor" pool-size="5"/>-->

</beans>
